{
  "date": "2026-03-25",
  "title": "瑞典新闻 — 2026年03月25日",
  "audio_url": "digests/2026-03-25.mp3",
  "duration_seconds": 366,
  "stories": [
    {
      "headline": "End-of-life injections given to non-dying 92-year-old in care home",
      "summary": "Uppdrag granskning reveals misuse of end-of-life sedation in elderly care",
      "source": "SVT Nyheter",
      "link": "https://www.svt.se/nyheter/granskning/ug/ulla-britt-fick-sprutor-for-livets-slut-fast-hon-inte-var-doende"
    },
    {
      "headline": "Liberals cross Riksdag barrier for first time since 2022",
      "summary": "Party hits 4.5% in SvD/Demoskop poll after SD voters switch",
      "source": "Expressen",
      "link": "https://www.expressen.se/nyheter/politik/liberalerna-ar-over-riksdagssparren-i-ny-opinionsmatning/"
    },
    {
      "headline": "Doctor shortcut: medical license despite low exam scores",
      "summary": "Radio Ekot reveals fast-track licensing bypassing normal academic thresholds",
      "source": "Sveriges Radio Ekot",
      "link": "https://www.sverigesradio.se/artikel/9183554"
    },
    {
      "headline": "Klippan double murder verdict handed down today",
      "summary": "58-year-old sentenced for brutal killing of couple in their home",
      "source": "SVT Nyheter",
      "link": "https://www.svt.se/nyheter/lokalt/helsingborg/livstid-eller-tidsbestamt-fangelse-for-dubbelmordet-i-klippan-idag-kommer-domen"
    },
    {
      "headline": "Sala-Heby energy defies government, keeps contested power charge",
      "summary": "Energy company refuses to drop charge despite minister pressure",
      "source": "SVT Nyheter",
      "link": "https://www.svt.se/nyheter/lokalt/vastmanland/sala-heby-energi-trotsar-regeringen-behaller-kritiserad-effektavgift"
    },
    {
      "headline": "New garbage law creates backlash over unequal rules for homeowners",
      "summary": "Townhouse owners in Vällingby call packaging rules unfair and costly",
      "source": "SVT Nyheter",
      "link": "https://www.svt.se/nyheter/lokalt/stockholm/kritik-mot-nya-soplagen-orattvist-att-smahus-inte-har-samma-regler"
    },
    {
      "headline": "AI used to analyze healthcare incident reports in Sweden",
      "summary": "Large language models deployed to improve patient safety data review",
      "source": "AI Sweden",
      "link": "https://www.ai.se/en/news/large-language-models-analyze-healthcare-incidents"
    },
    {
      "headline": "Vilhelmina councillors rage at new tax proposal favouring rich municipalities",
      "summary": "Reform would penalise tax-raising councils, reward tax-cutting ones",
      "source": "SVT Nyheter",
      "link": "https://www.svt.se/nyheter/lokalt/vasterbotten/vilhelminas-kommunalrad-rasar-mot-nya-skatteforslaget-rika-blir-rikare"
    },
    {
      "headline": "DN questions wisdom of cutting petrol tax again",
      "summary": "Editorial warns tax cuts entrench fossil fuel dependency",
      "source": "DN",
      "link": "https://www.dn.se/ledare/hur-smart-ar-det-egentligen-att-sanka-bensinskatten-igen/"
    },
    {
      "headline": "Are young Swedes really getting worse mentally?",
      "summary": "DN investigates rising psychiatric diagnoses among Swedish youth",
      "source": "DN",
      "link": "https://www.dn.se/sverige/fakta-i-fragan-mar-unga-allt-samre/"
    }
  ]
}